LICENSE
README.md
setup.cfg
setup.py
src/traclus/__init__.py
src/traclus/traclus.py
src/traclus_python.egg-info/PKG-INFO
src/traclus_python.egg-info/SOURCES.txt
src/traclus_python.egg-info/dependency_links.txt
src/traclus_python.egg-info/requires.txt
src/traclus_python.egg-info/top_level.txt