Metadata-Version: 2.1
Name: traclus-python
Version: 1.0.1
Home-page: https://github.com/AdrielAmoguis/TRACLUS
Author: Adriel Isaiah Amoguis
Author-email: adriel.isaiah.amoguis@gmail.com
License: apache-2.0
Keywords: Trajectory Clustering
License-File: LICENSE
